examples/__init__.py
examples/config_scanner/__init__.py
examples/config_scanner/test_config_scanner.py
examples/dependency_checker/__init__.py
examples/dependency_checker/file1.py
examples/dependency_checker/test_dependency_checker.py
examples/eval_exec_scanner/__init__.py
examples/eval_exec_scanner/example1.py
examples/eval_exec_scanner/example2.py
examples/eval_exec_scanner/example3.py
examples/eval_exec_scanner/test_eval_exec_scanner.py
examples/permissions_checker/__init__.py
examples/permissions_checker/test_permissions_checker.py
examples/secrets_scanner/__init__.py
examples/secrets_scanner/example1.py
examples/secrets_scanner/test_secrets_scanner.py
purvi_safeguard-0.1.0.dist-info/METADATA
purvi_safeguard-0.1.0.dist-info/WHEEL
purvi_safeguard-0.1.0.dist-info/top_level.txt
purvi_safeguard-0.1.0.dist-info/RECORD
