Metadata-Version: 2.4
Name: purvi-safeguard
Version: 0.1.0
Summary: A project for scanning secrets, configs, dependencies, and permissions
Author: Your Name
Requires-Python: >=3.10
Requires-Dist: pyyaml==6.0.2
Requires-Dist: requests==2.32.3
Requires-Dist: packaging==25.0
Requires-Dist: toml==0.10.2
Dynamic: author
Dynamic: requires-dist
Dynamic: requires-python
Dynamic: summary
